resources_rc.py
holocrontoolset-4.0.0b15.dist-info/licenses/LICENSE
toolset/__init__.py
toolset/__main__.py
toolset/main_app.py
toolset/main_init.py
toolset/main_settings.py
toolset/blender/__init__.py
toolset/blender/commands.py
toolset/blender/detection.py
toolset/blender/integration.py
toolset/blender/ipc_client.py
toolset/blender/serializers.py
toolset/config/__init__.py
toolset/config/config_info.py
toolset/config/config_update.py
toolset/config/config_version.py
toolset/data/__init__.py
toolset/data/indoormap.py
toolset/data/installation.py
toolset/data/me_controls.py
toolset/data/misc.py
toolset/data/settings.py
toolset/data/indoorkit/__init__.py
toolset/data/indoorkit/indoorkit_base.py
toolset/data/indoorkit/indoorkit_loader.py
toolset/data/indoorkit/indoorkit_utils.py
toolset/data/indoorkit/qt_preview.py
toolset/gui/__init__.py
toolset/gui/editor.py
toolset/gui/common/__init__.py
toolset/gui/common/debugger.py
toolset/gui/common/filters.py
toolset/gui/common/language_server_client.py
toolset/gui/common/localization.py
toolset/gui/common/style/__init__.py
toolset/gui/common/style/delegates.py
toolset/gui/common/style/palette_utils.py
toolset/gui/common/style/theme_manager.py
toolset/gui/common/style/vscode_style.py
toolset/gui/common/widgets/__init__.py
toolset/gui/common/widgets/breadcrumbs_widget.py
toolset/gui/common/widgets/code_editor.py
toolset/gui/common/widgets/collapsible.py
toolset/gui/common/widgets/combobox.py
toolset/gui/common/widgets/command_palette.py
toolset/gui/common/widgets/debug_callstack_widget.py
toolset/gui/common/widgets/debug_variables_widget.py
toolset/gui/common/widgets/debug_watch_widget.py
toolset/gui/common/widgets/find_replace_widget.py
toolset/gui/common/widgets/progressbar.py
toolset/gui/common/widgets/syntax_highlighter.py
toolset/gui/common/widgets/test_config_widget.py
toolset/gui/common/widgets/tree.py
toolset/gui/dialogs/__init__.py
toolset/gui/dialogs/about.py
toolset/gui/dialogs/asyncloader.py
toolset/gui/dialogs/blender_choice.py
toolset/gui/dialogs/clone_module.py
holocrontoolset-4.0.0b15.dist-info/METADATA
holocrontoolset-4.0.0b15.dist-info/WHEEL
holocrontoolset-4.0.0b15.dist-info/entry_points.txt
holocrontoolset-4.0.0b15.dist-info/top_level.txt
holocrontoolset-4.0.0b15.dist-info/RECORD
