Metadata-Version: 2.4
Name: holocrontoolset
Version: 4.0.0b15
Summary: A PyQt-backed program with a collection of tools and editors that make it easy to work with kotor files
Author: NickHugi
Maintainer-email: th3w1zard1 <halomastar@gmail.com>
License: LGPL-3.0-or-later
Project-URL: Homepage, https://github.com/OldRepublicDevs/PyKotor
Project-URL: Documentation, https://github.com/OldRepublicDevs/PyKotor/wiki
Project-URL: Repository, https://github.com/OldRepublicDevs/PyKotor.git
Project-URL: Issues, https://github.com/OldRepublicDevs/PyKotor/issues
Project-URL: Changelog, https://github.com/OldRepublicDevs/PyKotor/releases
Keywords: kotor,kotor1,kotor2,tsl,star-wars,knights-of-the-old-republic,modding,toolset,editor,gff,dlg,module-designer,pyqt5,opengl,3d,holocron,pykotor,bioware
Classifier: Development Status :: 5 - Production/Stable
Classifier: Intended Audience :: End Users/Desktop
Classifier: Intended Audience :: Developers
Classifier: License :: OSI Approved :: GNU Lesser General Public License v3 or later (LGPLv3+)
Classifier: Operating System :: OS Independent
Classifier: Programming Language :: Python :: 3
Classifier: Programming Language :: Python :: 3.8
Classifier: Programming Language :: Python :: 3.9
Classifier: Programming Language :: Python :: 3.10
Classifier: Programming Language :: Python :: 3.11
Classifier: Programming Language :: Python :: 3.12
Classifier: Programming Language :: Python :: 3.13
Classifier: Programming Language :: Python :: 3.14
Classifier: Topic :: Games/Entertainment
Classifier: Topic :: Games/Entertainment :: Role-Playing
Classifier: Topic :: Multimedia :: Graphics :: 3D Modeling
Classifier: Topic :: Text Editors :: Integrated Development Environments (IDE)
Classifier: Environment :: X11 Applications :: Qt
Classifier: Environment :: Win32 (MS Windows)
Classifier: Environment :: MacOS X
Requires-Python: >=3.8
License-File: LICENSE
Requires-Dist: pykotor[all]>=2.0.5
Requires-Dist: certifi>=2021.10.8
Requires-Dist: idna>=3.11
Requires-Dist: Markdown<3.9,>=3.4.4; python_version < "3.9"
Requires-Dist: Markdown>=3.4.4; python_version >= "3.9"
Requires-Dist: numpy<1.25.0,>=1.19.0; python_version < "3.9"
Requires-Dist: numpy>=1.19.0; python_version >= "3.9"
Requires-Dist: PyQt6<6.10.1,>=6.6.1; python_version == "3.8"
Requires-Dist: PyQt6>=6.10.1; python_version >= "3.9"
Requires-Dist: PyQt6-Qt6<6.10.1,>=6.6.1; python_version == "3.8"
Requires-Dist: PyQt6-Qt6>=6.10.1; python_version >= "3.9"
Requires-Dist: PyQt6-sip<13.10.3,>=12.10; python_version < "3.10"
Requires-Dist: PyQt6-sip>=13.10.3; python_version >= "3.10"
Requires-Dist: PyQt5-Qt5>=5.15; python_version == "3.8"
Requires-Dist: PyQt5-sip>=12.10; python_version == "3.8"
Requires-Dist: PyQt5>=5.15; python_version == "3.8"
Requires-Dist: PySide6; platform_python_implementation == "PyPy" and python_version >= "3.9"
Requires-Dist: PySide6>=6.10.1; platform_python_implementation == "PyPy" and python_version >= "3.9"
Requires-Dist: PySide6_Addons>=6.10.1; platform_python_implementation == "PyPy" and python_version >= "3.9"
Requires-Dist: PySide6_Essentials>=6.10.1; platform_python_implementation == "PyPy" and python_version >= "3.9"
Requires-Dist: qtpy>=2.4.3
Requires-Dist: requests<2.32.0,>=2.25.0; python_version < "3.9"
Requires-Dist: requests>=2.25.0; python_version >= "3.9"
Requires-Dist: urllib3<2.0.0,>=1.26.0; python_version < "3.9"
Requires-Dist: urllib3>=1.26.0; python_version >= "3.9"
Requires-Dist: jsonpickle>=4.1.1
Requires-Dist: send2trash>=1.8.3
Requires-Dist: comtypes>=1.4.0; sys_platform == "win32"
Requires-Dist: PyYAML>=6.0
Requires-Dist: Pillow>=9.5; platform_python_implementation == "CPython"
Requires-Dist: Pillow<11.1.0,>10; platform_python_implementation == "PyPy"
Provides-Extra: updater
Requires-Dist: requests<2.32,>=2.27; extra == "updater"
Requires-Dist: certifi==2021.10.8; extra == "updater"
Requires-Dist: pycryptodome>=3.19.0; extra == "updater"
Provides-Extra: qt6
Requires-Dist: PyQt6>=6.6.1; extra == "qt6"
Provides-Extra: pyside6
Requires-Dist: PySide6>=6.6.3.1; extra == "pyside6"
Provides-Extra: dev
Requires-Dist: pytest-qt>=4.2.0; extra == "dev"
Requires-Dist: pytest-xvfb>=3.0.0; extra == "dev"
Requires-Dist: types-Pillow; extra == "dev"
Requires-Dist: types-Send2Trash; extra == "dev"
Dynamic: license-file
